__init__.py
detectors.py
detectors_world.py
detectors_world-0.0.2.dist-info/LICENSE
detectors_world-0.0.2.dist-info/METADATA
detectors_world-0.0.2.dist-info/WHEEL
detectors_world-0.0.2.dist-info/top_level.txt
detectors_world-0.0.2.dist-info/RECORD
