Metadata-Version: 2.1
Name: detectors-world
Version: 0.0.2
Summary: Detectors World is a Python package created for building Computer Vision applications in easy and handy way.
Home-page: https://github.com/MeqdadDev/detectors-world
Author: Meqdad Dev
Author-email: meqdad.darweesh@gmail.com
Classifier: Programming Language :: Python :: 3
Classifier: License :: OSI Approved :: MIT License
Classifier: Operating System :: OS Independent
Classifier: Topic :: Scientific/Engineering :: Artificial Intelligence
Classifier: Topic :: Scientific/Engineering :: Artificial Life
Classifier: Topic :: Scientific/Engineering :: Image Processing
Classifier: Topic :: Scientific/Engineering :: Image Recognition
Classifier: Topic :: Scientific/Engineering :: Information Analysis
Classifier: Topic :: Utilities
License-File: LICENSE
Requires-Dist: mediapipe (>=0.9.0.1)
Requires-Dist: opencv-python (>=4.1.2.30)
